napari_broadcastable_points/__init__.py
napari_broadcastable_points/_points.py
napari_broadcastable_points-0.5.1.post2.dist-info/METADATA
napari_broadcastable_points-0.5.1.post2.dist-info/WHEEL
napari_broadcastable_points-0.5.1.post2.dist-info/licenses/LICENSE
napari_broadcastable_points-0.5.1.post2.dist-info/RECORD
