Metadata-Version: 2.4
Name: napari-broadcastable-points
Version: 0.5.1.post2
Project-URL: Homepage, https://github.com/ianhi/napari-broadcastable-points#napari-broadcastable-points
Project-URL: Documentation, https://github.com/ianhi/napari-broadcastable-points#napari-broadcastable-points
Project-URL: Repository, https://github.com/ianhi/napari-broadcastable-ponts.git
Author-email: Ian Hunt-Isaak <ianhuntisaak@gmail.com>
License: BSD 3-Clause License
License-File: LICENSE
Classifier: Development Status :: 4 - Beta
Classifier: Intended Audience :: Developers
Classifier: Intended Audience :: Science/Research
Classifier: License :: OSI Approved :: BSD License
Classifier: Operating System :: OS Independent
Classifier: Programming Language :: Python
Classifier: Programming Language :: Python :: 3
Classifier: Programming Language :: Python :: 3.8
Classifier: Programming Language :: Python :: 3.9
Classifier: Programming Language :: Python :: 3.10
Classifier: Programming Language :: Python :: 3.11
Classifier: Topic :: System :: Hardware
Classifier: Topic :: System :: Hardware :: Hardware Drivers
Classifier: Topic :: Utilities
Requires-Python: >=3.11
Requires-Dist: napari==0.5.0
Provides-Extra: cli
Requires-Dist: rich>=10.2.0; extra == 'cli'
Requires-Dist: typer>=0.4.2; extra == 'cli'
Provides-Extra: dev
Requires-Dist: black; extra == 'dev'
Requires-Dist: ipython; extra == 'dev'
Requires-Dist: mypy; extra == 'dev'
Requires-Dist: pdbpp; extra == 'dev'
Requires-Dist: pre-commit; extra == 'dev'
Requires-Dist: pytest; extra == 'dev'
Requires-Dist: pytest-cov; extra == 'dev'
Requires-Dist: rich; extra == 'dev'
Requires-Dist: ruff; extra == 'dev'
Requires-Dist: types-psutil; extra == 'dev'
Provides-Extra: docs
Requires-Dist: mkdocs-material; extra == 'docs'
Requires-Dist: mkdocs>=1.4; extra == 'docs'
Requires-Dist: mkdocstrings-python==1.1.2; extra == 'docs'
Requires-Dist: mkdocstrings==0.22.0; extra == 'docs'
Provides-Extra: testing
Requires-Dist: pyqt6; extra == 'testing'
Requires-Dist: pytest; extra == 'testing'
Requires-Dist: pytest-cov; extra == 'testing'
Requires-Dist: pytest-qt; extra == 'testing'
Requires-Dist: qtpy; extra == 'testing'
Requires-Dist: rich; extra == 'testing'
Requires-Dist: typer; extra == 'testing'
